metald/__init__.py
metald/_version.py
metald/github/__init__.py
metald/github/auth.py
metald/tex/__init__.py
metald/tex/lsstdoc.py
metald-0.1.0b3.dist-info/DESCRIPTION.rst
metald-0.1.0b3.dist-info/METADATA
metald-0.1.0b3.dist-info/RECORD
metald-0.1.0b3.dist-info/WHEEL
metald-0.1.0b3.dist-info/metadata.json
metald-0.1.0b3.dist-info/top_level.txt
