Metadata-Version: 2.0
Name: metald
Version: 0.1.0b3
Summary: LSST project metadata synthesis and JSON-LD export library.
Home-page: https://github.com/lsst-sqre/metald
Author: Association of Universities for Research in Astronomy, Inc.
Author-email: jsick@lsst.org
License: MIT
Keywords: lsst
Platform: UNKNOWN
Classifier: Development Status :: 4 - Beta
Classifier: License :: OSI Approved :: MIT License
Classifier: Programming Language :: Python :: 3.5
Classifier: Programming Language :: Python :: 3.6
Requires-Dist: pyjwt (>=1.4.2)
Requires-Dist: requests (>=2.13.0)
